music_downloader/__init__.py
music_downloader/downloader.py
qa_download-1.0.7.dist-info/METADATA
qa_download-1.0.7.dist-info/WHEEL
qa_download-1.0.7.dist-info/entry_points.txt
qa_download-1.0.7.dist-info/top_level.txt
qa_download-1.0.7.dist-info/RECORD
