Metadata-Version: 2.1
Name: qa_download
Version: 1.0.7
Summary: A tool for downloading music with embedded metadata and lyrics.
Home-page: https://github.com/AQaddora/music_downloader
Author: Ahmed Qaddoura
Author-email: aqaddora96@gmail.com
Requires-Python: >=3.7
Requires-Dist: yt-dlp
Requires-Dist: requests
Requires-Dist: beautifulsoup4
Requires-Dist: mutagen
Requires-Dist: colorama
